automatedai/__init__.py
automatedai/automatedai.py
automatedai-0.5.dist-info/LICENSE
automatedai-0.5.dist-info/METADATA
automatedai-0.5.dist-info/WHEEL
automatedai-0.5.dist-info/top_level.txt
automatedai-0.5.dist-info/RECORD
