Metadata-Version: 2.1
Name: automatedai
Version: 0.5
Summary: Automated.ai Python Client Library
Home-page: https://github.com/pypa/automatedai
Author: James Barfield
Author-email: info@automated.ai
License: UNKNOWN
Platform: UNKNOWN
Classifier: Development Status :: 3 - Alpha
Classifier: Programming Language :: Python :: 2
Classifier: Programming Language :: Python :: 3
Classifier: License :: OSI Approved :: MIT License
Classifier: Operating System :: OS Independent
Requires-Dist: requests
Requires-Dist: opencv-python
Requires-Dist: numpy
